client/__init__.py
client/client/__init__.py
client/client/client.py
client/client/client_db.py
client/client/client_socket.py
client/client/win_contact_add.py
client/client/win_contact_del.py
client/client/win_main.py
client/client/win_main_code.py
client/common/__init__.py
client/common/decors.py
client/common/errors.py
client/common/settings.py
client/common/utils.py
client/logs/__init__.py
client/logs/conf_client_log.py
client/unit_tests/__init__.py
client/unit_tests/test_client.py
client/unit_tests/test_server.py
client/unit_tests/test_utils.py
client/unit_tests/test_utils2.py
ib_message_client-0.0.4.data/scripts/client_run
ib_message_client-0.0.4.dist-info/METADATA
ib_message_client-0.0.4.dist-info/WHEEL
ib_message_client-0.0.4.dist-info/top_level.txt
ib_message_client-0.0.4.dist-info/RECORD
