Metadata-Version: 2.1
Name: ib-message-client
Version: 0.0.4
Summary: Client part of Server to client messanger
Home-page: https://pypi.org/project/ib-message-client/
Author: Igor Burakov
Author-email: iburako8@yandex.ru
License: UNKNOWN
Platform: UNKNOWN
Requires-Dist: PyQt5
Requires-Dist: sqlalchemy
Requires-Dist: pycryptodome
Requires-Dist: pycryptodomex
